CHANGES.txt
LICENSE.txt
MANIFEST.in
README.rst
requirements.txt
setup.py
docs/source/api.rst
docs/source/fetcher.rst
docs/source/index.rst
docs/source/wbdata.rst
tests/__init__.py
tests/__main__.py
wbdata/__init__.py
wbdata/api.py
wbdata/fetcher.py
wbdata.egg-info/PKG-INFO
wbdata.egg-info/SOURCES.txt
wbdata.egg-info/dependency_links.txt
wbdata.egg-info/requires.txt
wbdata.egg-info/top_level.txt