Metadata-Version: 1.1
Name: wbdata
Version: 0.2.7
Summary: A library to access World Bank data
Home-page: https://github.com/oliversherouse/wbdata
Author: Oliver Sherouse
Author-email: oliver.sherouse@gmail.com
License: UNKNOWN
Platform: UNKNOWN
Classifier: Development Status :: 4 - Beta
Classifier: Intended Audience :: Science/Research
Classifier: License :: OSI Approved :: GNU General Public License v2 or later (GPLv2+)
Classifier: Operating System :: OS Independent
Classifier: Topic :: Scientific/Engineering
Classifier: Programming Language :: Python
Classifier: Programming Language :: Python :: 2
Classifier: Programming Language :: Python :: 3
